{"class":"DepictionStackView","tintColor":"","title":"Contact Support","views":[{"class":"DepictionMarkdownView","markdown":"Ryan Petrich  is the maintainer of the package \"Activator\". Please contact them via email for any questions on this version of the package."},{"class":"DepictionTableButtonView","title":"Email Maintainer","action":"mailto:hoponthespot@gmail.com","openExternal":"true","tintColor":""},{"class":"DepictionMarkdownView","markdown":"If you found a mistake in the depiction or cannot download the package, you can reach out to the maintainer of the \"Encyclopedia's Repo (Random Crap)\" repo, Encyclopedia."},{"class":"DepictionTableButtonView","title":"Email Repo Maintainer","action":"mailto:hoponthespot@gmail.com","openExternal":"true","tintColor":""}]}